{
    "timestamp": "1463714771961",
    "msg": "查询成功",
    "isSuccess": "0",
    "resultData": [{
        "name": "进场A图片",
        "url": "http://prep.tingjiandan.com/mgr/order/getOrderImageFile/2/7850b842953f4d5687b164644c02f630",
        "uploadDateTime": "20170101000000",
        "pmParkId": "asfdfsdfsdfsd",
        "pmParkName": "朝阳大悦城测试停车场",
        "parkExitId": "dfbdfghdfgdfghdfh",
        "parkExit": "岗亭"
    }, {
        "name": "进场A图片",
        "url": "http://prep.tingjiandan.com/mgr/order/getOrderImageFile/2/7850b842953f4d5687b164644c02f630",
        "uploadDateTime": "20170101000000",
        "pmParkId": "asfdfsdfsdfsd",
        "pmParkName": "朝阳大悦城测试停车场",
        "parkExitId": "dfbdfghdfgdfghdfh",
        "parkExit": "岗亭"
    }, {
        "name": "进场A图片",
        "url": "http://prep.tingjiandan.com/mgr/order/getOrderImageFile/2/7850b842953f4d5687b164644c02f630",
        "uploadDateTime": "20170101000000",
        "pmParkId": "asfdfsdfsdfsd",
        "pmParkName": "朝阳大悦城测试停车场",
        "parkExitId": "dfbdfghdfgdfghdfh",
        "parkExit": "岗亭"
    }, {
        "name": "进场A图片",
        "url": "http://prep.tingjiandan.com/mgr/order/getOrderImageFile/2/7850b842953f4d5687b164644c02f630",
        "uploadDateTime": "20170101000000",
        "pmParkId": "asfdfsdfsdfsd",
        "pmParkName": "朝阳大悦城测试停车场",
        "parkExitId": "dfbdfghdfgdfghdfh",
        "parkExit": "岗亭"
    }, {
        "name": "进场A图片",
        "url": "http://prep.tingjiandan.com/mgr/order/getOrderImageFile/2/7850b842953f4d5687b164644c02f630",
        "uploadDateTime": "20170101000000",
        "pmParkId": "asfdfsdfsdfsd",
        "pmParkName": "朝阳大悦城测试停车场",
        "parkExitId": "dfbdfghdfgdfghdfh",
        "parkExit": "岗亭"
    }, {
        "name": "进场A图片",
        "url": "http://prep.tingjiandan.com/mgr/order/getOrderImageFile/2/7850b842953f4d5687b164644c02f630",
        "uploadDateTime": "20170101000000",
        "pmParkId": "asfdfsdfsdfsd",
        "pmParkName": "朝阳大悦城测试停车场",
        "parkExitId": "dfbdfghdfgdfghdfh",
        "parkExit": "岗亭"
    }, {
        "name": "进场A图片",
        "url": "http://prep.tingjiandan.com/mgr/order/getOrderImageFile/2/7850b842953f4d5687b164644c02f630",
        "uploadDateTime": "20170101000000",
        "pmParkId": "asfdfsdfsdfsd",
        "pmParkName": "朝阳大悦城测试停车场",
        "parkExitId": "dfbdfghdfgdfghdfh",
        "parkExit": "岗亭"
    }]
}